{
  "_format": "hh-sol-cache-2",
  "files": {
    "/Users/bmschwartz/Development/fix-my-pic/contracts/ImageBounty.sol": {
      "lastModificationDate": 1719608202166,
      "contentHash": "fe48d49889c87b436a593c5395a13ab6",
      "sourceName": "contracts/ImageBounty.sol",
      "solcConfig": {
        "version": "0.8.24",
        "settings": {
          "evmVersion": "paris",
          "optimizer": {
            "enabled": false,
            "runs": 200
          },
          "outputSelection": {
            "*": {
              "*": [
                "abi",
                "evm.bytecode",
                "evm.deployedBytecode",
                "evm.methodIdentifiers",
                "metadata"
              ],
              "": [
                "ast"
              ]
            }
          }
        }
      },
      "imports": [],
      "versionPragmas": [
        "^0.8.0"
      ],
      "artifacts": [
        "ImageBounty"
      ]
    },
    "/Users/bmschwartz/Development/fix-my-pic/contracts/ImageBountyFactory.sol": {
      "lastModificationDate": 1719232260612,
      "contentHash": "66610be473fa28a43b76c5c197bb5740",
      "sourceName": "contracts/ImageBountyFactory.sol",
      "solcConfig": {
        "version": "0.8.24",
        "settings": {
          "evmVersion": "paris",
          "optimizer": {
            "enabled": false,
            "runs": 200
          },
          "outputSelection": {
            "*": {
              "*": [
                "abi",
                "evm.bytecode",
                "evm.deployedBytecode",
                "evm.methodIdentifiers",
                "metadata"
              ],
              "": [
                "ast"
              ]
            }
          }
        }
      },
      "imports": [
        "./ImageBounty.sol"
      ],
      "versionPragmas": [
        "^0.8.0"
      ],
      "artifacts": [
        "ImageBountyFactory"
      ]
    }
  }
}
